lib_work_login/__init__.py
lib_work_login/__main__.py
lib_work_login/work_login.py
lib_work_login-0.1.4.dist-info/LICENSE
lib_work_login-0.1.4.dist-info/METADATA
lib_work_login-0.1.4.dist-info/WHEEL
lib_work_login-0.1.4.dist-info/entry_points.txt
lib_work_login-0.1.4.dist-info/top_level.txt
lib_work_login-0.1.4.dist-info/RECORD
