Metadata-Version: 2.1
Name: lib-work-login
Version: 0.1.4
Summary: Logs you into work
Home-page: https://github.com/jfuruness/lib_work_login.git
Author: Justin Furuness
Author-email: jfuruness@gmail.com
Maintainer: Justin Furuness
Maintainer-email: jfuruness@gmail.com
License: BSD
Download-URL: https://github.com/jfuruness/lib_work_login.git
Project-URL: Bug Tracker, https://github.com/pypa/sampleproject/issues
Keywords: Furuness,Login,login,terminal
Platform: UNKNOWN
Classifier: Environment :: Console
Classifier: Environment :: Web Environment
Classifier: Intended Audience :: Developers
Classifier: License :: OSI Approved :: BSD License
Classifier: Operating System :: POSIX :: Linux
Classifier: Programming Language :: Python :: 3
Requires-Python: >=3.6
Requires-Dist: pynput
